setup.py
lrs/__init__.py
lrs/keras.py
lrs.egg-info/PKG-INFO
lrs.egg-info/SOURCES.txt
lrs.egg-info/dependency_links.txt
lrs.egg-info/entry_points.txt
lrs.egg-info/not-zip-safe
lrs.egg-info/requires.txt
lrs.egg-info/top_level.txt