Metadata-Version: 1.0
Name: lrs
Version: 0.1.6
Summary: Save you training data online
Home-page: https://learning-rates.com
Author: Ilya Ovdin
Author-email: iovdin@gmail.com
License: Apache License 2.0
Platform: UNKNOWN
